{
  "record": {
    "index": 12,
    "filename": "20260427_181654.jpg",
    "file_path": "/Users/aliebrahimi/Documents/Saman Salamat/Extract text from files/Extract-text-from-medical-documents/samples/selected samples/20260427_181654.jpg",
    "file_ext": ".jpg",
    "mime_type": "image/jpeg",
    "file_size_kb": 36.8,
    "status": "needs_manual_review",
    "warnings": "low_structured_data",
    "quality_status": "needs_preprocessing",
    "quality_score": 0.49,
    "quality_issues": "",
    "width": 765,
    "height": 1020,
    "ocr_success": true,
    "ocr_confidence": 0.634,
    "ocr_text_length": 296,
    "ocr_source": "image_ocr_variants",
    "best_ocr_variant": "mild_contrast_rot90",
    "best_psm": 6,
    "medical_ok": true,
    "relevance_score": 1.0,
    "medical_hits": "urine;wbc;rbc;آزمایشگاه;آزمايشگاه;پزشک;پذیرش",
    "document_type": "lab",
    "document_type_confidence": 1.0,
    "document_signals": "urine;wbc;rbc;آزمایشگاه;آزمايشگاه",
    "common_field_count": 3,
    "lab_result_count": 2,
    "radiology_field_count": 0,
    "patient_name_found": false,
    "date_found": false,
    "age_found": false,
    "sex_found": true,
    "text_path": "/Users/aliebrahimi/Documents/Saman Salamat/Extract text from files/Extract-text-from-medical-documents/notebook_outputs/selected_samples_v3/texts/0012_20260427_181654.txt"
  },
  "quality": {
    "status": "needs_preprocessing",
    "overall_quality_score": 0.49,
    "issues": [],
    "width": 765,
    "height": 1020,
    "brightness_mean": 149.93,
    "contrast_std": 26.46,
    "laplacian_variance": 124.78
  },
  "ocr_meta": {
    "ocr_success": true,
    "ocr_confidence": 0.6335185185185186,
    "source": "image_ocr_variants",
    "best_variant": "mild_contrast_rot90",
    "best_psm": 6,
    "best_lang": "eng+fas",
    "candidate_count": 84,
    "candidate_scores": [
      {
        "variant": "mild_contrast_rot90",
        "psm": 6,
        "lang": "eng+fas",
        "score": 18.3,
        "len": 296,
        "conf": 0.634,
        "error": null
      },
      {
        "variant": "light_autocontrast_rot90",
        "psm": 6,
        "lang": "eng+fas",
        "score": 16.27,
        "len": 289,
        "conf": 0.627,
        "error": null
      },
      {
        "variant": "original_oriented_rot90",
        "psm": 6,
        "lang": "eng+fas",
        "score": 15.79,
        "len": 220,
        "conf": 0.623,
        "error": null
      },
      {
        "variant": "original_oriented_rot90",
        "psm": 11,
        "lang": "eng+fas",
        "score": 14.13,
        "len": 172,
        "conf": 0.677,
        "error": null
      },
      {
        "variant": "mild_contrast_rot90",
        "psm": 6,
        "lang": "eng",
        "score": 13.12,
        "len": 244,
        "conf": 0.416,
        "error": null
      },
      {
        "variant": "light_autocontrast_rot90",
        "psm": 6,
        "lang": "eng",
        "score": 13.12,
        "len": 247,
        "conf": 0.412,
        "error": null
      },
      {
        "variant": "mild_contrast_rot90",
        "psm": 11,
        "lang": "eng+fas",
        "score": 12.29,
        "len": 171,
        "conf": 0.701,
        "error": null
      },
      {
        "variant": "light_autocontrast_rot90",
        "psm": 11,
        "lang": "eng+fas",
        "score": 11.57,
        "len": 171,
        "conf": 0.7,
        "error": null
      },
      {
        "variant": "original_oriented_rot90",
        "psm": 6,
        "lang": "eng",
        "score": 10.57,
        "len": 172,
        "conf": 0.342,
        "error": null
      },
      {
        "variant": "mild_contrast_rot90",
        "psm": 11,
        "lang": "eng",
        "score": 10.15,
        "len": 157,
        "conf": 0.483,
        "error": null
      },
      {
        "variant": "light_autocontrast_rot90",
        "psm": 11,
        "lang": "eng",
        "score": 10.14,
        "len": 161,
        "conf": 0.476,
        "error": null
      },
      {
        "variant": "original_oriented_rot90",
        "psm": 11,
        "lang": "eng",
        "score": 9.96,
        "len": 155,
        "conf": 0.489,
        "error": null
      },
      {
        "variant": "threshold_fallback",
        "psm": 6,
        "lang": "eng+fas",
        "score": 6.89,
        "len": 273,
        "conf": 0.426,
        "error": null
      },
      {
        "variant": "threshold_fallback",
        "psm": 11,
        "lang": "eng",
        "score": 6.55,
        "len": 159,
        "conf": 0.371,
        "error": null
      },
      {
        "variant": "threshold_fallback",
        "psm": 11,
        "lang": "eng+fas",
        "score": 6.37,
        "len": 164,
        "conf": 0.516,
        "error": null
      }
    ],
    "meta": {}
  },
  "parts": [
    {
      "part_type": "common_field",
      "section": "header",
      "field_name": "center_name",
      "value": "153 شماره‎ HIT پزشکی‎ آزمایشگاه",
      "result_numeric": null,
      "unit": null,
      "reference_range": null,
      "flag": null,
      "method": null,
      "confidence": 0.7,
      "source_text": "153 شماره‎ HIT پزشکی‎ آزمایشگاه",
      "index": 12,
      "filename": "20260427_181654.jpg",
      "document_status": "needs_manual_review",
      "document_type": "lab",
      "text_path": "/Users/aliebrahimi/Documents/Saman Salamat/Extract text from files/Extract-text-from-medical-documents/notebook_outputs/selected_samples_v3/texts/0012_20260427_181654.txt"
    },
    {
      "part_type": "common_field",
      "section": "header",
      "field_name": "sex",
      "value": "female",
      "result_numeric": null,
      "unit": null,
      "reference_range": null,
      "flag": null,
      "method": null,
      "confidence": 0.85,
      "source_text": "“ {\n153 شماره‎ HIT پزشکی‎ آزمایشگاه\n3 WS 8) okie متری‎ 35 - مرکزی آباد جنت\n32392907 -44492805 ن‎\n73 05 تلفن‎\n(gaz: Je o خازنی‎ فرژانه اخانم کنده ol 29-13 پذیرش:‎ شماره\n‘Urine Analysis\nImacroscopic\nj 754 Microscopic\n|Unne Analysis WBC. 8-10\n| Color Yellow RBC مو‎\n| Semi-Clear Epithelial Cells وه‎",
      "index": 12,
      "filename": "20260427_181654.jpg",
      "document_status": "needs_manual_review",
      "document_type": "lab",
      "text_path": "/Users/aliebrahimi/Documents/Saman Salamat/Extract text from files/Extract-text-from-medical-documents/notebook_outputs/selected_samples_v3/texts/0012_20260427_181654.txt"
    },
    {
      "part_type": "common_field",
      "section": "header",
      "field_name": "doctor_name",
      "value": "ی‎ آزمایشگاه",
      "result_numeric": null,
      "unit": null,
      "reference_range": null,
      "flag": null,
      "method": null,
      "confidence": 0.75,
      "source_text": "پزشکی‎ آزمایشگاه",
      "index": 12,
      "filename": "20260427_181654.jpg",
      "document_status": "needs_manual_review",
      "document_type": "lab",
      "text_path": "/Users/aliebrahimi/Documents/Saman Salamat/Extract text from files/Extract-text-from-medical-documents/notebook_outputs/selected_samples_v3/texts/0012_20260427_181654.txt"
    },
    {
      "part_type": "lab_result",
      "section": "hematology",
      "field_name": "WBC",
      "test_name_raw": "WBC",
      "value": "8",
      "result_numeric": 8.0,
      "unit": null,
      "reference_range": null,
      "flag": null,
      "method": null,
      "confidence": 0.65,
      "source_text": "WBC. 8-10\n| Color Yellow RBC مو‎\n| Semi-Clear Epithelial Cells وه‎",
      "index": 12,
      "filename": "20260427_181654.jpg",
      "document_status": "needs_manual_review",
      "document_type": "lab",
      "text_path": "/Users/aliebrahimi/Documents/Saman Salamat/Extract text from files/Extract-text-from-medical-documents/notebook_outputs/selected_samples_v3/texts/0012_20260427_181654.txt"
    },
    {
      "part_type": "lab_result",
      "section": "urine_analysis",
      "field_name": "Color",
      "test_name_raw": "Color",
      "value": "Yellow",
      "result_numeric": null,
      "unit": null,
      "reference_range": null,
      "flag": null,
      "method": null,
      "confidence": 0.65,
      "source_text": "s Imacroscopic j 754 Microscopic |Unne Analysis WBC. 8-10 | Color Yellow RBC مو‎ | Semi-Clear Epithelial Cells وه‎",
      "index": 12,
      "filename": "20260427_181654.jpg",
      "document_status": "needs_manual_review",
      "document_type": "lab",
      "text_path": "/Users/aliebrahimi/Documents/Saman Salamat/Extract text from files/Extract-text-from-medical-documents/notebook_outputs/selected_samples_v3/texts/0012_20260427_181654.txt"
    }
  ],
  "text": "“ {\n153 شماره‎ HIT پزشکی‎ آزمایشگاه\n3 WS 8) okie متری‎ 35 - مرکزی آباد جنت\n32392907 -44492805 ن‎\n73 05 تلفن‎\n(gaz: Je o خازنی‎ فرژانه اخانم کنده ol 29-13 پذیرش:‎ شماره\n‘Urine Analysis\nImacroscopic\nj 754 Microscopic\n|Unne Analysis WBC. 8-10\n| Color Yellow RBC مو‎\n| Semi-Clear Epithelial Cells وه‎"
}